MANIFEST.in
setup.cfg
setup.py
lolologist/LeagueGothic-Regular.otf
lolologist/__init__.py
lolologist/cameras.py
lolologist/lolologist.py
lolologist/lolz.py
lolologist/repository.py
lolologist/tranzlator.json
lolologist/utils.py
lolologist.egg-info/PKG-INFO
lolologist.egg-info/SOURCES.txt
lolologist.egg-info/dependency_links.txt
lolologist.egg-info/entry_points.txt
lolologist.egg-info/not-zip-safe
lolologist.egg-info/requires.txt
lolologist.egg-info/top_level.txt