Metadata-Version: 1.1
Name: lolologist
Version: 0.5.4
Summary: A utility that automatically generates an image macro from your webcam whenever you commit to a git repository.
Home-page: https://github.com/arusahni/lolologist
Author: Aru Sahni
Author-email: arusahni@gmail.com
License: MPL 2.0
Download-URL: https://github.com/arusahni/lolologist/tarball/v0.5.3
Keywords: git,camera,webcam,commit,macro,image,lol,lulz,version,control
Platform: UNKNOWN
Classifier: Development Status :: 4 - Beta
Classifier: License :: OSI Approved :: Mozilla Public License 2.0 (MPL 2.0)
Classifier: Programming Language :: Python :: 2.7
Classifier: Programming Language :: Python :: 3
Classifier: Programming Language :: Python :: 3.4
Classifier: Programming Language :: Python :: Implementation :: CPython
Classifier: Programming Language :: Python :: Implementation :: PyPy
Classifier: Environment :: Console
Classifier: Operating System :: POSIX :: Linux
Classifier: Operating System :: MacOS :: MacOS X
Classifier: Topic :: Multimedia :: Graphics :: Capture
Classifier: Topic :: Utilities
Classifier: Topic :: Software Development :: Version Control
